odoo/addons/sale_type_confirmation_requirement_rules/README.rst
odoo/addons/sale_type_confirmation_requirement_rules/__init__.py
odoo/addons/sale_type_confirmation_requirement_rules/__manifest__.py
odoo/addons/sale_type_confirmation_requirement_rules/i18n/es.po
odoo/addons/sale_type_confirmation_requirement_rules/models/__init__.py
odoo/addons/sale_type_confirmation_requirement_rules/models/sale_order.py
odoo/addons/sale_type_confirmation_requirement_rules/models/sale_order_requirement_rule.py
odoo/addons/sale_type_confirmation_requirement_rules/models/sale_order_type.py
odoo/addons/sale_type_confirmation_requirement_rules/security/ir.model.access.csv
odoo/addons/sale_type_confirmation_requirement_rules/static/description/icon.png
odoo/addons/sale_type_confirmation_requirement_rules/views/sale_order_requirement_rule_views.xml
odoo/addons/sale_type_confirmation_requirement_rules/views/sale_order_type_view.xml
odoo_addon_sale_type_confirmation_requirement_rules-15.0.1.0.1.dist-info/METADATA
odoo_addon_sale_type_confirmation_requirement_rules-15.0.1.0.1.dist-info/WHEEL
odoo_addon_sale_type_confirmation_requirement_rules-15.0.1.0.1.dist-info/top_level.txt
odoo_addon_sale_type_confirmation_requirement_rules-15.0.1.0.1.dist-info/RECORD
